RegistratorHelperService/__init__.py
RegistratorHelperService/__main__.py
RegistratorHelperService/const.py
RegistratorHelperService/service.py
pih_rgst_help-1.13.dist-info/METADATA
pih_rgst_help-1.13.dist-info/WHEEL
pih_rgst_help-1.13.dist-info/entry_points.txt
pih_rgst_help-1.13.dist-info/top_level.txt
pih_rgst_help-1.13.dist-info/RECORD
