Metadata-Version: 2.1
Name: pih-rgst-help
Version: 1.13
Summary: PIH Registrator helper service package
Home-page: https://pacifichosp.com/
Author: Nikita Karachentsev
Author-email: it@pacifichosp.com
License: MIT
Requires-Dist: ipih
Requires-Dist: pih-mio
